{
    "pessoas" : [
        {
            "id" : "1",
            "nome" : "Rodrigo Barreto",
            "email" : "barretorodrigo@gmail.com",
            "dataDeNascimento" : "1987-04-20"
        },
        {
            "id" : "2",
            "nome" : "Julio Cesar De Azevedo",
            "email" : "Azevedo@gmail.com",
            "dataDeNascimento" : "2004-05-19"
        },
        {
            "id" : "3",
            "nome" : "Richard Cesar",
            "email" : "richard@gmail.com",
            "dataDeNascimento" : "2001-06-12"
        },
        {
            "id" : "4",
            "nome" : "Vinicius Silveira",
            "email" : "v.silveira@gmail.com",
            "dataDeNascimento" : "2002-03-11"
        },
        {
            "id" : "5",
            "nome" : "Fernanda Guzzo",
            "email" : "fer.guzzo@gmail.com",
            "dataDeNascimento" : "2003-10-31"
        }
    ]
}